aiorchestra/__init__.py
aiorchestra/core/__init__.py
aiorchestra/core/context.py
aiorchestra/core/logger.py
aiorchestra/core/node.py
aiorchestra/core/noop.py
aiorchestra/core/utils.py
aiorchestra/tests/__init__.py
aiorchestra/tests/base.py
aiorchestra/tests/plugin.py
aiorchestra/tests/test_context_builder.py
aiorchestra/tests/test_context_serialization.py
aiorchestra/tests/test_deployments.py
aiorchestra/tests/test_nodes.py
aiorchestra/tests/test_plugin.py
aiorchestra-0.1.3.dist-info/DESCRIPTION.rst
aiorchestra-0.1.3.dist-info/METADATA
aiorchestra-0.1.3.dist-info/RECORD
aiorchestra-0.1.3.dist-info/WHEEL
aiorchestra-0.1.3.dist-info/metadata.json
aiorchestra-0.1.3.dist-info/top_level.txt
aiorchestra-0.1.3.dist-info/zip-safe
